doodlin_ai/__init__.py
doodlin_ai/datasets/__init__.py
doodlin_ai/datasets/dataloader.py
doodlin_ai/models/__init__.py
doodlin_ai/py.typed
doodlin_ai-0.0.2a2.dist-info/WHEEL
doodlin_ai-0.0.2a2.dist-info/METADATA
doodlin_ai-0.0.2a2.dist-info/RECORD
