Metadata-Version: 2.1
Name: doodlin-ai
Version: 0.0.2a2
Summary: Doodlin AI Archaiver
Home-page: https://doodlincorp.github.io/doodlin-ai
License: MIT
Author: 한일석
Author-email: x2ever.han@gmail.com
Requires-Python: >=3.8,<4.0
Classifier: Development Status :: 4 - Beta
Classifier: Intended Audience :: Developers
Classifier: License :: OSI Approved :: MIT License
Classifier: Operating System :: OS Independent
Classifier: Programming Language :: Python
Classifier: Programming Language :: Python :: 3
Classifier: Programming Language :: Python :: 3.8
Classifier: Programming Language :: Python :: 3.9
Classifier: Programming Language :: Python :: 3.10
Classifier: Programming Language :: Python :: 3.11
Classifier: Programming Language :: Python :: 3.8
Classifier: Programming Language :: Python :: 3.9
Classifier: Topic :: Software Development :: Libraries :: Python Modules
Classifier: Typing :: Typed
Requires-Dist: boto3 (>=1.26.37,<2.0.0)
Requires-Dist: huggingface (>=0.0.1,<0.0.2)
Requires-Dist: moto[all] (>=4.0.12,<5.0.0)
Requires-Dist: pandas (>=1.5.2,<2.0.0)
Requires-Dist: pillow (>=9.3.0,<10.0.0)
Requires-Dist: pre-commit (>=2.21.0,<3.0.0)
Requires-Dist: tqdm (>=4.64.1,<5.0.0)
Requires-Dist: types-pillow (>=9.3.0.4,<10.0.0.0)
Requires-Dist: types-tqdm (>=4.64.7.9,<5.0.0.0)
Project-URL: Documentation, https://doodlincorp.github.io/doodlin-ai
Project-URL: Repository, https://github.com/doodlincorp/doodlin-ai
